easyopt/__init__.py
easyopt/cmd.py
easyopt/utils.py
easyopt/lib/__init__.py
easyopt/lib/lib.py
easyopt/src/__init__.py
easyopt/src/heartbeat.py
easyopt/src/optimize.py
easyopt/src/socketserver.py
easyopt-0.3.1.dist-info/LICENSE
easyopt-0.3.1.dist-info/METADATA
easyopt-0.3.1.dist-info/WHEEL
easyopt-0.3.1.dist-info/entry_points.txt
easyopt-0.3.1.dist-info/top_level.txt
easyopt-0.3.1.dist-info/RECORD
