Metadata-Version: 2.1
Name: easyopt
Version: 0.3.1
Home-page: 
Author: Federico A. Galatolo
Author-email: federico.galatolo@ing.unipi.it
Classifier: Programming Language :: Python :: 3.7
Classifier: License :: OSI Approved :: GNU General Public License v3 (GPLv3)
Classifier: Operating System :: OS Independent
Classifier: Development Status :: 4 - Beta
License-File: LICENSE
Requires-Dist: optuna ==3.5.0
Requires-Dist: PyYAML ==5.4.1
Requires-Dist: colorama ==0.4.4
